hikDriver/__init__.py
hikDriver/cli.py
hikDriver/hikDriver.py
hik_isapi-0.0.1.dist-info/METADATA
hik_isapi-0.0.1.dist-info/WHEEL
hik_isapi-0.0.1.dist-info/entry_points.txt
hik_isapi-0.0.1.dist-info/top_level.txt
hik_isapi-0.0.1.dist-info/RECORD
