Metadata-Version: 2.1
Name: hik-isapi
Version: 0.0.1
Summary: A simple CLI program for hikvison Cam
Home-page: https://github.com/rfooox/isapi
Author: rfooox
Author-email: rfooox@outlook.com
Classifier: Programming Language :: Python :: 3
Classifier: License :: OSI Approved :: MIT License
Classifier: Operating System :: OS Independent
Requires-Dist: requests
Requires-Dist: xmltodict
Requires-Dist: typer
